coinpouch/__init__.py
coinpouch/abstract_app.py
coinpouch/utils.py
coinpouch/asynchronous/__init__.py
coinpouch/asynchronous/caches/__init__.py
coinpouch/asynchronous/caches/abstract_cache.py
coinpouch/asynchronous/events/__init__.py
coinpouch/asynchronous/events/abstract_event_bus.py
coinpouch/asynchronous/queues/__init__.py
coinpouch/asynchronous/queues/abstract_queue.py
coinpouch/asynchronous/secrets/__init__.py
coinpouch/asynchronous/secrets/secrets.py
coinpouch/asynchronous/services/__init__.py
coinpouch/asynchronous/services/service.py
coinpouch/asynchronous/storages/__init__.py
coinpouch/asynchronous/storages/abstract_storage.py
coinpouch/caches/__init__.py
coinpouch/caches/abstract_cache.py
coinpouch/constants/__init__.py
coinpouch/constants/error_constants.py
coinpouch/events/__init__.py
coinpouch/events/abstract_event_bus.py
coinpouch/loggers/__init__.py
coinpouch/loggers/logger.py
coinpouch/models/__init__.py
coinpouch/models/abstract_model.py
coinpouch/models/attributes.py
coinpouch/models/base_object.py
coinpouch/models/base_table.py
coinpouch/models/errors.py
coinpouch/models/model.py
coinpouch/models/object.py
coinpouch/objects/__init__.py
coinpouch/objects/abstract_expiring_model_object.py
coinpouch/objects/abstract_model_object.py
coinpouch/objects/attribute.py
coinpouch/objects/object.py
coinpouch/queues/__init__.py
coinpouch/queues/abstract_queue.py
coinpouch/secrets/__init__.py
coinpouch/secrets/secrets.py
coinpouch/security/__init__.py
coinpouch/security/generic.py
coinpouch/services/__init__.py
coinpouch/services/service.py
coinpouch/storages/__init__.py
coinpouch/storages/abstract_storage.py
coinpouch-0.0.2.dist-info/licenses/LICENSE
coinpouch-0.0.2.dist-info/METADATA
coinpouch-0.0.2.dist-info/WHEEL
coinpouch-0.0.2.dist-info/top_level.txt
coinpouch-0.0.2.dist-info/RECORD
