Metadata-Version: 2.4
Name: coinpouch
Version: 0.0.2
Summary: Bootstrap code for developing AWS microservices
Author-email: Alexander Cheung <awcheung@gmail.com>
License-Expression: MIT
Classifier: Programming Language :: Python :: 3
Classifier: Operating System :: OS Independent
Requires-Python: >=3.10
License-File: LICENSE
Dynamic: license-file
